Metadata-Version: 2.4
Name: nai-t5-wrapper
Version: 1.0.0
Summary: HuggingFace-compatible wrapper for NovelAI's T5 with Flex Attention - supports T5, MT5, and UMT5
Project-URL: Homepage, https://github.com/bghira/nai-t5-wrapper
Project-URL: Issue Tracker, https://github.com/bghira/nai-t5-wrapper/issues
Author: NovelAI/Anlatan Inc., SimpleTuner Contributors
License: Apache-2.0
License-File: LICENSE
Keywords: flex-attention,mt5,novelai,t5,transformers,umt5
Classifier: Development Status :: 4 - Beta
Classifier: Intended Audience :: Developers
Classifier: Intended Audience :: Science/Research
Classifier: License :: OSI Approved :: Apache Software License
Classifier: Programming Language :: Python :: 3
Classifier: Programming Language :: Python :: 3.10
Classifier: Programming Language :: Python :: 3.11
Classifier: Programming Language :: Python :: 3.12
Classifier: Topic :: Scientific/Engineering :: Artificial Intelligence
Requires-Python: >=3.10
Requires-Dist: einops
Requires-Dist: pydantic
Requires-Dist: torch>=2.0
Provides-Extra: bench
Requires-Dist: tabulate; extra == 'bench'
Requires-Dist: triton; extra == 'bench'
Provides-Extra: hf
Requires-Dist: tokenizers; extra == 'hf'
Requires-Dist: transformers>=4.40; extra == 'hf'
Provides-Extra: sp
Requires-Dist: sentencepiece; extra == 'sp'
Provides-Extra: tensorizer
Requires-Dist: tensorizer; extra == 'tensorizer'
